{
  "choice": "ProposeNewTrade",
  "argument": {
    "ps": [{
      "id": "5454121752721",
      "p": "DEALER-D01"
    }, {
      "id": "5264151754007",
      "p": "CCP-P01"
    }],
    "base": {
      "timestamp": [{
        "qualification": "eventCreationDateTime",
        "dateTime": "2018-10-02T21:40:55.229+00:00[UTC]"
      }],
      "rosettaKey": "b91ac8d3",
      "eventDate": "2018-10-02",
      "primitive": {

      },
      "eventIdentifier": [{
        "issuerReference": {
          "reference": "UNKNOWN"
        },
        "assignedIdentifier": [{
          "version": 1,
          "identifier": {
            "value": "EJAPCGMWEZ"
          }
        }]
      }],
      "action": "New"
    },
    "after": {
      "contract": {
        "contractIdentifier": [{
          "issuerReference": {
            "reference": "5454121752721"
          },
          "assignedIdentifier": [{
            "version": 1,
            "identifier": {
              "value": "0EGNBBV3WA"
            }
          }]
        }, {
          "issuerReference": {
            "reference": "5264151754007"
          },
          "assignedIdentifier": [{
            "version": 1,
            "identifier": {
              "value": "0EGNBBV3WA"
            }
          }]
        }],
        "tradeDate": {
          "date": "2018-10-02"
        },
        "rosettaKey": "1947407",
        "party": [{
          "id": "5454121752721",
          "name": {
            "value": "DEALER-D01"
          },
          "partyId": [{
            "value": "5454121752721"
          }],
          "account": {
            "accountNumber": {
              "value": "D01823328500"
            }
          }
        }, {
          "id": "5264151754007",
          "name": {
            "value": "CCP-P01"
          },
          "partyId": [{
            "value": "5264151754007"
          }],
          "account": {
            "accountNumber": {
              "value": "P01547927812"
            }
          }
        }],
        "contractualProduct": {
          "productIdentification": {
            "primaryAssetClass": {
              "value": "InterestRate"
            },
            "productQualifier": "InterestRate_IRSwap_FixedFloat"
          },
          "economicTerms": {
            "rosettaKeyValue": "3d528e2a",
            "payout": {
              "interestRatePayout": [{
                "quantity": {
                  "notionalSchedule": {
                    "notionalStepSchedule": {
                      "initialValue": 900000000.00,
                      "currency": {
                        "value": "EUR"
                      }
                    }
                  }
                },
                "paymentDates": {
                  "calculationPeriodDatesReference": {
                    "reference": "floatingCalcPeriodDates"
                  },
                  "payRelativeTo": "CalculationPeriodEndDate",
                  "paymentDatesAdjustments": {
                    "businessCenters": {
                      "businessCenter": [{
                        "value": "EUTA"
                      }]
                    },
                    "businessDayConvention": "FOLLOWING"
                  },
                  "paymentFrequency": {
                    "period": "M",
                    "periodMultiplier": 6
                  }
                },
                "rosettaKey": "33485cda",
                "dayCountFraction": {
                  "value": "_30_360"
                },
                "rateSpecification": {
                  "floatingRate": {
                    "floatingRateIndex": {
                      "value": "EUR_EURIBOR_Reuters"
                    },
                    "indexTenor": {
                      "period": "M",
                      "periodMultiplier": 6
                    },
                    "spreadSchedule": [{
                      "initialValue": 0.003000
                    }],
                    "initialRate": 0.028438
                  }
                },
                "calculationPeriodDates": {
                  "calculationPeriodDatesAdjustments": {
                    "businessCenters": {
                      "businessCenter": [{
                        "value": "EUTA"
                      }]
                    },
                    "businessDayConvention": "FOLLOWING"
                  },
                  "id": "floatingCalcPeriodDates",
                  "calculationPeriodFrequency": {
                    "period": "M",
                    "periodMultiplier": 6,
                    "rollConvention": "_4"
                  },
                  "terminationDate": {
                    "adjustableDate": {
                      "dateAdjustments": {
                        "businessCenters": {
                          "businessCenter": [{
                            "value": "EUTA"
                          }]
                        },
                        "businessDayConvention": "FOLLOWING"
                      },
                      "unadjustedDate": "2021-10-04"
                    }
                  },
                  "effectiveDate": {
                    "adjustableDate": {
                      "dateAdjustments": {
                        "businessCenters": {
                          "businessCenter": [{
                            "value": "EUTA"
                          }]
                        },
                        "businessDayConvention": "FOLLOWING"
                      },
                      "unadjustedDate": "2018-10-04"
                    }
                  }
                },
                "resetDates": {
                  "fixingDates": {
                    "businessCenters": {
                      "businessCenter": [{
                        "value": "EUTA"
                      }]
                    },
                    "periodMultiplier": -2,
                    "dayType": "Business",
                    "businessDayConvention": "NONE",
                    "period": "D"
                  },
                  "resetFrequency": {
                    "period": "M",
                    "periodMultiplier": 6
                  },
                  "id": "resetDates",
                  "calculationPeriodDatesReference": {
                    "reference": "floatingCalcPeriodDates"
                  },
                  "resetRelativeTo": "CalculationPeriodStartDate",
                  "resetDatesAdjustments": {
                    "businessCenters": {
                      "businessCenter": [{
                        "value": "EUTA"
                      }]
                    },
                    "businessDayConvention": "FOLLOWING"
                  }
                },
                "payerReceiver": {
                  "payerPartyReference": {
                    "reference": "5454121752721"
                  },
                  "receiverPartyReference": {
                    "reference": "5264151754007"
                  }
                }
              }, {
                "quantity": {
                  "notionalSchedule": {
                    "notionalStepSchedule": {
                      "initialValue": 900000000.00,
                      "currency": {
                        "value": "EUR"
                      }
                    }
                  }
                },
                "paymentDates": {
                  "calculationPeriodDatesReference": {
                    "reference": "fixedCalcPeriodDates"
                  },
                  "payRelativeTo": "CalculationPeriodEndDate",
                  "paymentDatesAdjustments": {
                    "businessCenters": {
                      "businessCenter": [{
                        "value": "EUTA"
                      }]
                    },
                    "businessDayConvention": "FOLLOWING"
                  },
                  "paymentFrequency": {
                    "period": "Y",
                    "periodMultiplier": 1
                  }
                },
                "rosettaKey": "9d25a7bc",
                "dayCountFraction": {
                  "value": "_30_360"
                },
                "rateSpecification": {
                  "fixedRate": {
                    "initialValue": 0.014232
                  }
                },
                "calculationPeriodDates": {
                  "calculationPeriodDatesAdjustments": {
                    "businessCenters": {
                      "businessCenter": [{
                        "value": "EUTA"
                      }]
                    },
                    "businessDayConvention": "FOLLOWING"
                  },
                  "id": "fixedCalcPeriodDates",
                  "calculationPeriodFrequency": {
                    "period": "Y",
                    "periodMultiplier": 1,
                    "rollConvention": "_4"
                  },
                  "terminationDate": {
                    "adjustableDate": {
                      "dateAdjustments": {
                        "businessCenters": {
                          "businessCenter": [{
                            "value": "EUTA"
                          }]
                        },
                        "businessDayConvention": "FOLLOWING"
                      },
                      "unadjustedDate": "2021-10-04"
                    }
                  },
                  "effectiveDate": {
                    "adjustableDate": {
                      "dateAdjustments": {
                        "businessCenters": {
                          "businessCenter": [{
                            "value": "EUTA"
                          }]
                        },
                        "businessDayConvention": "FOLLOWING"
                      },
                      "unadjustedDate": "2018-10-04"
                    }
                  }
                },
                "payerReceiver": {
                  "payerPartyReference": {
                    "reference": "5264151754007"
                  },
                  "receiverPartyReference": {
                    "reference": "5454121752721"
                  }
                }
              }]
            }
          }
        }
      }
    }
  }
}
