{
  "choice": "ProposeNewTrade",
  "argument": {
    "ps": [{
      "id": "6456382944861",
      "p": "DEALER-D01"
    }, {
      "id": "7755090773988",
      "p": "CLIENT-C01"
    }],
    "base": {
      "timestamp": [{
        "qualification": "eventCreationDateTime",
        "dateTime": "2018-10-04T21:40:55.543+00:00[UTC]"
      }],
      "rosettaKey": "b39dd836",
      "eventDate": "2018-10-04",
      "primitive": {

      },
      "eventIdentifier": [{
        "issuerReference": {
          "reference": "UNKNOWN"
        },
        "assignedIdentifier": [{
          "version": 1,
          "identifier": {
            "value": "FUW9O13NLT"
          }
        }]
      }],
      "action": "New"
    },
    "after": {
      "contract": {
        "contractIdentifier": [{
          "issuerReference": {
            "reference": "6456382944861"
          },
          "assignedIdentifier": [{
            "version": 1,
            "identifier": {
              "value": "DTRLDEU0PY"
            }
          }]
        }, {
          "issuerReference": {
            "reference": "7755090773988"
          },
          "assignedIdentifier": [{
            "version": 1,
            "identifier": {
              "value": "DTRLDEU0PY"
            }
          }]
        }],
        "tradeDate": {
          "date": "2018-10-04"
        },
        "rosettaKey": "987d629e",
        "party": [{
          "id": "6456382944861",
          "name": {
            "value": "DEALER-D01"
          },
          "partyId": [{
            "value": "6456382944861"
          }],
          "account": {
            "accountNumber": {
              "value": "D01232071422"
            }
          }
        }, {
          "id": "7755090773988",
          "name": {
            "value": "CLIENT-C01"
          },
          "partyId": [{
            "value": "7755090773988"
          }],
          "account": {
            "accountNumber": {
              "value": "C01232409785"
            }
          }
        }],
        "contractualProduct": {
          "productIdentification": {
            "primaryAssetClass": {
              "value": "InterestRate"
            },
            "productQualifier": "InterestRate_IRSwap_Basis"
          },
          "economicTerms": {
            "rosettaKeyValue": "647b9c5",
            "payout": {
              "interestRatePayout": [{
                "quantity": {
                  "notionalSchedule": {
                    "notionalStepSchedule": {
                      "initialValue": 800000000.00,
                      "currency": {
                        "value": "USD"
                      }
                    }
                  }
                },
                "paymentDates": {
                  "calculationPeriodDatesReference": {
                    "reference": "floatingCalcPeriodDates"
                  },
                  "payRelativeTo": "CalculationPeriodEndDate",
                  "paymentDatesAdjustments": {
                    "businessCenters": {
                      "businessCenter": [{
                        "value": "USNY"
                      }]
                    },
                    "businessDayConvention": "FOLLOWING"
                  },
                  "paymentFrequency": {
                    "period": "M",
                    "periodMultiplier": 3
                  }
                },
                "rosettaKey": "ab5a886",
                "dayCountFraction": {
                  "value": "ACT_360"
                },
                "rateSpecification": {
                  "floatingRate": {
                    "floatingRateIndex": {
                      "value": "USD_LIBOR_BBA"
                    },
                    "indexTenor": {
                      "period": "M",
                      "periodMultiplier": 3
                    },
                    "spreadSchedule": [{
                      "initialValue": 0.005000
                    }],
                    "initialRate": 0.032021
                  }
                },
                "calculationPeriodDates": {
                  "calculationPeriodDatesAdjustments": {
                    "businessCenters": {
                      "businessCenter": [{
                        "value": "USNY"
                      }]
                    },
                    "businessDayConvention": "FOLLOWING"
                  },
                  "id": "floatingCalcPeriodDates",
                  "calculationPeriodFrequency": {
                    "period": "M",
                    "periodMultiplier": 3,
                    "rollConvention": "_9"
                  },
                  "terminationDate": {
                    "adjustableDate": {
                      "dateAdjustments": {
                        "businessCenters": {
                          "businessCenter": [{
                            "value": "USNY"
                          }]
                        },
                        "businessDayConvention": "FOLLOWING"
                      },
                      "unadjustedDate": "2019-10-09"
                    }
                  },
                  "effectiveDate": {
                    "adjustableDate": {
                      "dateAdjustments": {
                        "businessCenters": {
                          "businessCenter": [{
                            "value": "USNY"
                          }]
                        },
                        "businessDayConvention": "FOLLOWING"
                      },
                      "unadjustedDate": "2018-10-06",
                      "adjustedDate": {
                        "value": "2018-10-09"
                      }
                    }
                  }
                },
                "resetDates": {
                  "fixingDates": {
                    "businessCenters": {
                      "businessCenter": [{
                        "value": "GBLO"
                      }]
                    },
                    "periodMultiplier": -2,
                    "dayType": "Business",
                    "businessDayConvention": "NONE",
                    "period": "D"
                  },
                  "resetFrequency": {
                    "period": "M",
                    "periodMultiplier": 3
                  },
                  "id": "resetDates",
                  "calculationPeriodDatesReference": {
                    "reference": "floatingCalcPeriodDates"
                  },
                  "resetRelativeTo": "CalculationPeriodStartDate",
                  "resetDatesAdjustments": {
                    "businessCenters": {
                      "businessCenter": [{
                        "value": "GBLO"
                      }]
                    },
                    "businessDayConvention": "FOLLOWING"
                  }
                },
                "payerReceiver": {
                  "payerPartyReference": {
                    "reference": "6456382944861"
                  },
                  "receiverPartyReference": {
                    "reference": "7755090773988"
                  }
                }
              }, {
                "quantity": {
                  "notionalSchedule": {
                    "notionalStepSchedule": {
                      "initialValue": 800000000.00,
                      "currency": {
                        "value": "USD"
                      }
                    }
                  }
                },
                "paymentDates": {
                  "calculationPeriodDatesReference": {
                    "reference": "floatingCalcPeriodDates"
                  },
                  "payRelativeTo": "CalculationPeriodEndDate",
                  "paymentDatesAdjustments": {
                    "businessCenters": {
                      "businessCenter": [{
                        "value": "USNY"
                      }]
                    },
                    "businessDayConvention": "FOLLOWING"
                  },
                  "paymentFrequency": {
                    "period": "M",
                    "periodMultiplier": 6
                  }
                },
                "rosettaKey": "c3f1d115",
                "dayCountFraction": {
                  "value": "ACT_360"
                },
                "rateSpecification": {
                  "floatingRate": {
                    "floatingRateIndex": {
                      "value": "USD_LIBOR_BBA"
                    },
                    "indexTenor": {
                      "period": "M",
                      "periodMultiplier": 6
                    },
                    "spreadSchedule": [{
                      "initialValue": 0.005000
                    }],
                    "initialRate": 0.027914
                  }
                },
                "calculationPeriodDates": {
                  "calculationPeriodDatesAdjustments": {
                    "businessCenters": {
                      "businessCenter": [{
                        "value": "USNY"
                      }]
                    },
                    "businessDayConvention": "FOLLOWING"
                  },
                  "id": "floatingCalcPeriodDates",
                  "calculationPeriodFrequency": {
                    "period": "M",
                    "periodMultiplier": 6,
                    "rollConvention": "_9"
                  },
                  "terminationDate": {
                    "adjustableDate": {
                      "dateAdjustments": {
                        "businessCenters": {
                          "businessCenter": [{
                            "value": "USNY"
                          }]
                        },
                        "businessDayConvention": "FOLLOWING"
                      },
                      "unadjustedDate": "2019-10-09"
                    }
                  },
                  "effectiveDate": {
                    "adjustableDate": {
                      "dateAdjustments": {
                        "businessCenters": {
                          "businessCenter": [{
                            "value": "USNY"
                          }]
                        },
                        "businessDayConvention": "FOLLOWING"
                      },
                      "unadjustedDate": "2018-10-06",
                      "adjustedDate": {
                        "value": "2018-10-09"
                      }
                    }
                  }
                },
                "resetDates": {
                  "fixingDates": {
                    "businessCenters": {
                      "businessCenter": [{
                        "value": "GBLO"
                      }]
                    },
                    "periodMultiplier": -2,
                    "dayType": "Business",
                    "businessDayConvention": "NONE",
                    "period": "D"
                  },
                  "resetFrequency": {
                    "period": "M",
                    "periodMultiplier": 6
                  },
                  "id": "resetDates",
                  "calculationPeriodDatesReference": {
                    "reference": "floatingCalcPeriodDates"
                  },
                  "resetRelativeTo": "CalculationPeriodStartDate",
                  "resetDatesAdjustments": {
                    "businessCenters": {
                      "businessCenter": [{
                        "value": "GBLO"
                      }]
                    },
                    "businessDayConvention": "FOLLOWING"
                  }
                },
                "payerReceiver": {
                  "payerPartyReference": {
                    "reference": "7755090773988"
                  },
                  "receiverPartyReference": {
                    "reference": "6456382944861"
                  }
                }
              }]
            }
          }
        }
      }
    }
  }
}
